{
    "users": [
        {
            "id": 1,
            "name": "Chelsea",
            "location": "London",
            "catgories": ["shopping", "sightseeing", "photography"],
            "feed_image": "https://images.unsplash.com/photo-1587971315632-20288867c7bd?ixlib=rb-1.2.1&ixid=MnwxMjA3fDB8MHxwaG90by1wYWdlfHx8fGVufDB8fHx8&auto=format&fit=crop&w=735&q=80"
            
        },
        {
            "id": 2,
            "name": "Amirah",
            "location": "Madrid",
            "catgories": ["clubbing, museums, food"],
            "feed_image": ""
            
        },
        {
            "id": 3,
            "name": "Kyle",
            "location": "Honolulu",
            "catgories": ["surfing, "],
            "feed_image": "https://images.unsplash.com/photo-1537953773345-d172ccf13cf1?ixlib=rb-1.2.1&ixid=MnwxMjA3fDB8MHxzZWFyY2h8Nnx8YmFsaXxlbnwwfHwwfHw%3D&auto=format&fit=crop&w=800&q=60"
            
        },
        {
            "id": 4,
            "name": "Michael",
            "location": "Bali",
            "catgories": ["photography", "hiking", "clubbing"],
            "feed_image": "https://images.unsplash.com/photo-1537953773345-d172ccf13cf1?ixlib=rb-1.2.1&ixid=MnwxMjA3fDB8MHxzZWFyY2h8Nnx8YmFsaXxlbnwwfHwwfHw%3D&auto=format&fit=crop&w=800&q=60"
            
        },
        {
            "id": 5,
            "name": "Leah",
            "location": "Colorado",
            "catgories": ["hiking", "skiing", "shopping"],
            "feed_image": "https://cdn.pixabay.com/photo/2017/08/06/12/06/people-2591874__340.jpg"
            
        },
        {
            "id": 6,
            "name": "Jason",
            "location": "Maldives",
            "catgories": [],
            "feed_image": "https://cdn.pixabay.com/photo/2017/01/20/00/30/maldives-1993704__340.jpg"
            
        }

        
    ],

    "myprofile": [
        {
        "name": "Danielle",
        "username": "@daniellesworld",
        "profilepic": "https://images.unsplash.com/photo-1520466809213-7b9a56adcd45?ixlib=rb-1.2.1&ixid=MnwxMjA3fDB8MHxwaG90by1wYWdlfHx8fGVufDB8fHx8&auto=format&fit=crop&w=687&q=80",
        "postsNumber": "203",
        "followers": "3479",
        "following": "698",
        "bio": "Living the dream",
        "images": [
            {
            "id": "1",
            "image": "https://images.unsplash.com/photo-1605216663980-b7ca6e9f2451?ixlib=rb-1.2.1&      ixid=MnwxMjA3fDB8MHxwaG90by1wYWdlfHx8fGVufDB8fHx8&auto=format&fit=crop&w=807&q=80"
            }, 
            {
            "id": "2",
            "image": "https://images.unsplash.com/photo-1603279560898-9eb1a6516d60?ixlib=rb-1.2.1&ixid=MnwxMjA3fDB8MHxwaG90by1wYWdlfHx8fGVufDB8fHx8&auto=format&fit=crop&w=1374&q=80"
            }, 
            {
            "id": "3",
            "image": "https://images.unsplash.com/photo-1601401521820-966ad2e30d8e?ixlib=rb-1.2.1&ixid=MnwxMjA3fDB8MHxwaG90by1wYWdlfHx8fGVufDB8fHx8&auto=format&fit=crop&w=735&q=80"
            },
            {
            "id": "4",
             "image": "https://images.unsplash.com/photo-1613591797545-3ff9eba2ac34?ixlib=rb-1.2.1&ixid=MnwxMjA3fDB8MHxwaG90by1wYWdlfHx8fGVufDB8fHx8&auto=format&fit=crop&w=1160&q=80"
            },
            {
            "id": "5",
            "image": "https://images.unsplash.com/photo-1452838269443-c86e6a3134f9?ixlib=rb-1.2.1&ixid=MnwxMjA3fDB8MHxzZWFyY2h8MXx8bWV4aWNvJTIwY2l0eXxlbnwwfDJ8MHx8&auto=format&fit=crop&w=800&q=60"
            },
            {
            "id": "6",
            "image": "https://images.unsplash.com/photo-1585206908231-155cf84bc5b1?ixlib=rb-1.2.1&ixid=MnwxMjA3fDB8MHxzZWFyY2h8M3x8bWV4aWNvJTIwYXJjaGl0ZWN0dXJlfGVufDB8MnwwfHw%3D&auto=format&fit=crop&w=800&q=60"
            }
    ]
        }


    ],

    "favorited_content": [
        {
            "id": 1,
            "name": "Chelsea Smith",
            "location": "London",
            "catgories": ["shopping", "sightseeing", "photography"],
            "image": "https://images.unsplash.com/photo-1587971315632-20288867c7bd?ixlib=rb-1.2.1&ixid=MnwxMjA3fDB8MHxwaG90by1wYWdlfHx8fGVufDB8fHx8&auto=format&fit=crop&w=735&q=80"
            
        },
        {
            "id": 2,
            "name": "Amirah Khan",
            "location": "Madrid",
            "catgories": ["Clubbing", "Museums", "Food"],
            "image": "https://images.unsplash.com/photo-1585206908231-155cf84bc5b1?ixlib=rb-1.2.1&ixid=MnwxMjA3fDB8MHxzZWFyY2h8M3x8bWV4aWNvJTIwYXJjaGl0ZWN0dXJlfGVufDB8MnwwfHw%3D&auto=format&fit=crop&w=800&q=60"   
        },
        {
            "id": 3,
            "name": "Kyle Bayliss",
            "location": "Honolulu",
            "catgories": ["surfing"],
            "image": "https://images.unsplash.com/photo-1537953773345-d172ccf13cf1?ixlib=rb-1.2.1&ixid=MnwxMjA3fDB8MHxzZWFyY2h8Nnx8YmFsaXxlbnwwfHwwfHw%3D&auto=format&fit=crop&w=800&q=60"
            
        },
        {
            "id": 4,
            "name": "Michael Taylor",
            "location": "Bali",
            "catgories": ["photography", "hiking", "clubbing"],
            "image": "https://images.unsplash.com/photo-1601401521820-966ad2e30d8e?ixlib=rb-1.2.1&ixid=MnwxMjA3fDB8MHxwaG90by1wYWdlfHx8fGVufDB8fHx8&auto=format&fit=crop&w=735&q=800"
            
        },
        {
            "id": 5,
            "name": "Leah Phillips",
            "location": "Colorado",
            "catgories": ["hiking", "skiing", "shopping"],
            "image": "https://images.unsplash.com/photo-1603279560898-9eb1a6516d60?ixlib=rb-1.2.1&ixid=MnwxMjA3fDB8MHxwaG90by1wYWdlfHx8fGVufDB8fHx8&auto=format&fit=crop&w=1374&q=80"
            
        },
        {
            "id": 6,
            "name": "Jason Doe",
            "location": "Maldives",
            "catgories": [],
            "image": "https://cdn.pixabay.com/photo/2017/01/20/00/30/maldives-1993704__340.jpg"
            
        },
        {
            "id": 7,
            "name": "Deacon Saint-John",
            "location": "Honolulu",
            "catgories": ["Lakes", "England", "Mountains"],
            "image": "https://mediaim.expedia.com/destination/1/21b50a20e8d18cb7a94b138f6a90fc3a.jpg"
            
        },
        {
            "id": 8,
            "name": "Sarah O'Brien",
            "location": "Vienna",
            "catgories": ["Photography", "Europe", "Clubbing"],
            "image": "https://encrypted-tbn0.gstatic.com/images?q=tbn:ANd9GcRUqtJuqsdj0do3YbJp77LkIp4KBr2V38nUA95Ht7ak1W64KXJAMqVKomKN_w3mxop6rks&usqp=CAU"
        }
    ]
}